{
  "ComponentIndexes": {},
  "ControlUniqueGuids": {},
  "ControlUniqueIds": {
    "App": 1,
    "bebebc1e-b3b2-4049-abe0-9d6a81d63330": 530,
    "Button1": 72,
    "Button1_10": 282,
    "Button1_11": 111,
    "Button1_12": 116,
    "Button1_13": 112,
    "Button1_14": 323,
    "Button1_15": 117,
    "Button1_16": 283,
    "Button1_17": 324,
    "Button1_18": 40,
    "Button1_19": 41,
    "Button1_20": 224,
    "Button1_21": 227,
    "Button1_5": 376,
    "Button1_8": 95,
    "Button1_9": 96,
    "Button11_1": 99,
    "Button11_5": 286,
    "Button11_6": 327,
    "Button11_7": 44,
    "Button11_8": 230,
    "Button13_4": 98,
    "Button13_5": 285,
    "Button13_6": 326,
    "Button13_7": 43,
    "Button13_8": 229,
    "Button2": 247,
    "Button3": 388,
    "Button3_1": 460,
    "Button3_2": 405,
    "Button3_3": 424,
    "Button3_4": 441,
    "Button3_5": 477,
    "Button3_6": 497,
    "Button3_7": 514,
    "Button5": 162,
    "Button5_1": 163,
    "Button6": 365,
    "Button6_1": 167,
    "Button6_4": 97,
    "Button6_6": 284,
    "Button6_7": 325,
    "Button6_8": 42,
    "Button6_9": 228,
    "Button7": 272,
    "Button8": 314,
    "Button9": 436,
    "Button9_1": 398,
    "Button9_10": 473,
    "Button9_11": 488,
    "Button9_12": 491,
    "Button9_13": 495,
    "Button9_14": 506,
    "Button9_15": 509,
    "Button9_16": 523,
    "Button9_17": 526,
    "Button9_2": 419,
    "Button9_3": 453,
    "Button9_4": 401,
    "Button9_5": 416,
    "Button9_7": 433,
    "Button9_8": 450,
    "Button9_9": 470,
    "ButtonGuardar_1": 58,
    "ButtonGuardar1": 214,
    "CdigoCrystal_11": 447,
    "CdigoCrystal_12": 520,
    "CdigoCrystal_13": 341,
    "CdigoCrystal_17": 342,
    "CdigoCrystal_4": 395,
    "CdigoCrystal_5": 413,
    "CdigoCrystal_6": 430,
    "CdigoCrystal_7": 467,
    "CdigoCrystal_8": 485,
    "CdigoCrystal_9": 503,
    "CdigoCrystal9": 259,
    "CdigoMaterial": 263,
    "Checkbox4": 253,
    "Circle1": 310,
    "Circle2_1": 108,
    "Circle2_2": 114,
    "Codigo_rgb": 312,
    "codigoInput": 69,
    "color_Crystal": 237,
    "ColorCrystal": 374,
    "ColorCrystal_1": 64,
    "ColorCrystal_2": 65,
    "Colores_Crystal": 32,
    "ColoresSeleccionados": 4,
    "colorInput": 68,
    "ComboBox1": 243,
    "ComboBox1_1": 156,
    "ComboBox2": 375,
    "ComboBox2_1": 244,
    "ComboBox2_2": 143,
    "ComboBox3": 174,
    "ComboBox4": 166,
    "ConAlerta44/2": 415,
    "ConAlerta44/2_1": 487,
    "ConAlerta78/2": 397,
    "ConAlerta78/2_1": 469,
    "ConAlertaElastico": 432,
    "ConAlertaElastico_1": 505,
    "ConAlertaLycra": 449,
    "ConAlertaLycra_1": 522,
    "Container_barraNavegacionColoresCrystal": 33,
    "Container_barraNavegacionPantone": 219,
    "Container_barraNavegacionRGB_Eneas": 275,
    "Container_barraNavegacionvanisados": 88,
    "Container_barraNavegacionVanisados": 316,
    "Container_Botton": 271,
    "Container_codigoRGB": 293,
    "Container_cuadro": 124,
    "Container_Filtros": 232,
    "Container_FiltrosColorcrystal": 63,
    "Container_FiltrosVanisados": 370,
    "Container_Gallery2": 248,
    "Container_GestionVanizados": 138,
    "Container_pop_up": 197,
    "Container_Popup": 47,
    "Container1": 288,
    "Container12": 257,
    "Container2_1": 215,
    "Container2_2": 59,
    "Container2_3": 366,
    "Container2_4": 289,
    "Container2_5": 102,
    "Container22": 306,
    "Container3": 170,
    "Container3_1": 173,
    "Container6": 337,
    "Containerbarratabla": 144,
    "ContainerBarratabla": 299,
    "ContainerbarratablaGallery5": 377,
    "ContainerBase": 346,
    "containerBaseCrystal": 46,
    "ContainerBotones": 161,
    "ContainerBotton": 313,
    "ContainercCoTargeta": 233,
    "ContainerColorSeleccion": 5,
    "ContainercomboBox": 139,
    "ContainerComentarios": 101,
    "ContainerCuadro": 141,
    "ContainerDaToscolor_1": 443,
    "ContainerDatoscolor_2": 426,
    "ContainerDaToscolor_2": 516,
    "ContainerDatoscolor_3": 409,
    "ContainerDatoscolor_4": 391,
    "ContainerDatoscolor_5": 463,
    "ContainerDatoscolor_6": 481,
    "ContainerDatoscolor_7": 499,
    "ContaineRectangulo": 80,
    "Containerinputtabla": 151,
    "ContainerLandingPage": 107,
    "ContainerLogo": 90,
    "ContainerLogo_1": 277,
    "ContainerLogo_2": 318,
    "ContainerLogo_3": 35,
    "ContainerLogo_4": 221,
    "ContainerLogo_5": 7,
    "ContainerPadre": 13,
    "ContainerRecomendado": 347,
    "ContainerRGB": 119,
    "ContainerRoles": 164,
    "ContainerSuge_vanisado": 179,
    "ContainerSugerencia": 176,
    "ContainertarColor": 371,
    "Containertarjetapequeña": 19,
    "ContainerTarjetas": 251,
    "ContainerTarjetasGran": 14,
    "ContaITarjeta": 75,
    "Contenedor": 106,
    "ContenedorBase": 196,
    "ContenedorPopPapSugerencia": 329,
    "contenedorTarjetaElastico": 421,
    "contenedorTarjetaElastico_1": 493,
    "contenedorTarjetaLycra": 438,
    "contenedorTarjetaLycra_1": 511,
    "contenedortarjetaVani.44/2": 403,
    "contenedortarjetaVani.44/2_1": 475,
    "contenedortarjetaVani.78/2": 386,
    "contenedortarjetaVani.78/2_1": 458,
    "ConteneTarjeR_RGB": 122,
    "Datosdelcolor": 394,
    "Datosdelcolor_1": 412,
    "Datosdelcolor_2": 429,
    "Datosdelcolor_3": 466,
    "Datosdelcolor_4": 484,
    "Datosdelcolor_5": 502,
    "Datosdelcolor_6": 446,
    "Datosdelcolor_7": 519,
    "Datosdelcolor9": 262,
    "DescargarPDF": 273,
    "Descripcin": 265,
    "Dropdown1": 241,
    "Dropdown1_1": 356,
    "Dropdown1_2": 354,
    "Dropdown2": 242,
    "DropdownColores": 71,
    "DropdownMaterial": 70,
    "Elasticoexpuesto": 382,
    "Elasticoexpuesto_1": 381,
    "Elasticoexpuesto_2": 380,
    "Elasticoexpuesto_6": 383,
    "Elasticoexpuesto_7": 379,
    "EtiquetaCodigoSAP": 55,
    "EtiquetaDescripcion": 53,
    "EtiquetaTextoCodigoSAP": 206,
    "EtiquetaTextoColorCrystal": 204,
    "EtiquetaTextoNombreColor": 202,
    "EtiquetaTextopantone": 200,
    "fed87c5f-ccd6-47f6-b984-bfaff76af83a": 529,
    "Galeria_Alternativa": 456,
    "Galeria_Datos": 384,
    "Gallery1": 73,
    "Gallery2": 249,
    "Gallery3": 120,
    "Gallery3_1": 11,
    "Gallery4": 168,
    "Gallery5": 177,
    "GalleryRGB": 304,
    "galleryTemplate1": 74,
    "galleryTemplate2": 250,
    "galleryTemplate3": 121,
    "galleryTemplate3_1": 12,
    "galleryTemplate3_2": 305,
    "galleryTemplate4": 169,
    "galleryTemplate5": 178,
    "galleryTemplate5_1": 385,
    "galleryTemplate5_2": 457,
    "Host": 3,
    "Icon1": 332,
    "Icon1_1": 298,
    "Icon1_3": 218,
    "Icon1_4": 62,
    "Icon1_5": 369,
    "Icon1_6": 292,
    "Icon1_7": 105,
    "Icon10": 448,
    "Icon10_1": 431,
    "Icon10_10": 474,
    "Icon10_11": 486,
    "Icon10_12": 492,
    "Icon10_13": 504,
    "Icon10_14": 510,
    "Icon10_15": 521,
    "Icon10_16": 527,
    "Icon10_2": 414,
    "Icon10_3": 396,
    "Icon10_4": 345,
    "Icon10_5": 402,
    "Icon10_6": 420,
    "Icon10_7": 437,
    "Icon10_8": 454,
    "Icon10_9": 468,
    "Icon11": 123,
    "Icon12": 217,
    "Icon12_1": 61,
    "Icon12_2": 368,
    "Icon12_3": 291,
    "Icon12_4": 104,
    "Icon13": 18,
    "Icon17": 186,
    "Icon2": 295,
    "Icon3": 269,
    "Icon4": 31,
    "Icon5": 30,
    "Icon6": 352,
    "Icon7": 79,
    "Icon8": 187,
    "Icon9": 349,
    "IconCerrarPopup": 199,
    "IconCerrarPopup_1": 49,
    "Image1": 9,
    "Image1_10": 231,
    "Image1_5": 100,
    "Image1_6": 287,
    "Image1_7": 110,
    "Image1_8": 328,
    "Image1_9": 45,
    "Image10": 280,
    "Image11": 93,
    "Image12": 226,
    "Image13": 281,
    "Image14": 39,
    "Image15": 94,
    "Image16": 270,
    "Image2": 322,
    "Image22": 118,
    "Image3": 175,
    "Image3_2": 417,
    "Image3_3": 434,
    "Image3_4": 451,
    "Image3_5": 399,
    "Image3_6": 471,
    "Image3_7": 489,
    "Image3_8": 507,
    "Image3_9": 524,
    "Image4": 171,
    "Image5": 91,
    "Image5_1": 278,
    "Image5_2": 319,
    "Image5_3": 36,
    "Image5_4": 222,
    "Image5_5": 8,
    "Image6": 225,
    "Image7": 38,
    "Image9": 321,
    "Imagen_de_Carga": 344,
    "Label1": 78,
    "Label1_1": 84,
    "Label1_2": 86,
    "Label1_3": 140,
    "Label1_4": 147,
    "Label1_5": 148,
    "Label1_6": 149,
    "Label1_7": 146,
    "Label1_8": 150,
    "Label10": 364,
    "Label10_1": 109,
    "Label10_2": 115,
    "Label11": 211,
    "Label12": 194,
    "Label13": 210,
    "Label14": 21,
    "Label14_1": 22,
    "Label15": 235,
    "Label16": 189,
    "Label17": 188,
    "Label18": 180,
    "Label18_1": 181,
    "Label18_2": 182,
    "Label18_3": 183,
    "Label18_4": 184,
    "Label18_5": 185,
    "Label19": 212,
    "Label2": 10,
    "Label2_1": 297,
    "Label2_2": 302,
    "Label2_3": 303,
    "Label2_4": 296,
    "Label2_5": 301,
    "Label20": 261,
    "Label21": 213,
    "Label22": 23,
    "Label22_1": 28,
    "Label22_2": 24,
    "Label22_3": 25,
    "Label22_4": 27,
    "Label22_5": 26,
    "Label22_6": 29,
    "Label22_7": 16,
    "Label23": 172,
    "Label25": 126,
    "Label25_1": 127,
    "Label25_10": 133,
    "Label25_11": 136,
    "Label25_2": 135,
    "Label25_3": 130,
    "Label25_4": 131,
    "Label25_5": 134,
    "Label25_6": 137,
    "Label25_7": 128,
    "Label25_8": 132,
    "Label25_9": 129,
    "Label3": 357,
    "Label3_1": 359,
    "Label3_10": 350,
    "Label3_11": 351,
    "Label3_12": 362,
    "Label3_13": 348,
    "Label3_2": 343,
    "Label3_3": 340,
    "Label3_4": 198,
    "Label3_5": 48,
    "Label3_6": 353,
    "Label3_7": 360,
    "Label3_8": 358,
    "Label3_9": 355,
    "Label4": 400,
    "Label4_1": 472,
    "Label4_2": 418,
    "Label4_3": 435,
    "Label4_4": 452,
    "Label4_5": 490,
    "Label4_6": 508,
    "Label4_7": 525,
    "Label5": 389,
    "Label5_1": 406,
    "Label5_2": 461,
    "Label5_3": 423,
    "Label5_4": 440,
    "Label5_5": 478,
    "Label5_6": 496,
    "Label5_7": 513,
    "Label6": 165,
    "Label6_3": 92,
    "Label6_4": 113,
    "Label6_5": 279,
    "Label6_6": 320,
    "Label6_7": 37,
    "Label6_8": 223,
    "Label7": 77,
    "Label7_1": 83,
    "Label7_2": 85,
    "Label8": 363,
    "Label8_1": 54,
    "Label8_5": 50,
    "Label8_7": 52,
    "Label9": 393,
    "Label9_1": 411,
    "Label9_2": 428,
    "Label9_3": 465,
    "Label9_4": 483,
    "Label9_5": 501,
    "Label9_6": 445,
    "Label9_7": 339,
    "Label9_8": 518,
    "LabelCapturaRGB_NO_BORRAR": 256,
    "labelCoColor": 260,
    "LabelCodigoSap": 264,
    "LabelDescripcion": 266,
    "LabelNombre": 268,
    "materiaPrima": 455,
    "materiaPrima_1": 528,
    "Materiaprimaprincipal_1": 67,
    "Materiaprimaprincipal_2": 66,
    "Materiaprimaprincipal1": 238,
    "Mssimilar1_7": 334,
    "Mssimilar1_8": 333,
    "Mssimilar4": 254,
    "Nombredecolor": 267,
    "Pantalla_GestionVanisados": 87,
    "Pantalla_Pantone": 195,
    "Pantalla_RGB_ENEAS": 274,
    "Pantalla_Vanisados": 315,
    "Pantonecdigo": 239,
    "Pantonecdigo_1": 236,
    "Rectangle1": 20,
    "Rectangle1_2": 89,
    "Rectangle1_3": 276,
    "Rectangle1_4": 317,
    "Rectangle1_5": 34,
    "Rectangle1_6": 220,
    "Rectangle10_1": 153,
    "Rectangle10_2": 154,
    "Rectangle10_3": 155,
    "Rectangle10_4": 152,
    "Rectangle11_2": 6,
    "Rectangle12": 125,
    "Rectangle15": 387,
    "Rectangle15_1": 76,
    "Rectangle15_2": 82,
    "Rectangle15_3": 459,
    "Rectangle15_5": 331,
    "Rectangle151": 252,
    "Rectangle16": 390,
    "Rectangle16_1": 462,
    "Rectangle16_3": 336,
    "Rectangle161": 255,
    "Rectangle18": 258,
    "Rectangle2": 335,
    "Rectangle211": 234,
    "Rectangle211_1": 142,
    "Rectangle3": 300,
    "Rectangle4": 81,
    "Rectangle40": 378,
    "Rectangle5": 373,
    "Rectangle5_1": 372,
    "Rectangle6": 308,
    "Rectangle6_2": 309,
    "Rectangle7": 145,
    "Rectangle73": 392,
    "Rectangle73_1": 464,
    "Rectangle73_3": 338,
    "Rectangle8": 15,
    "Rectangle86": 404,
    "Rectangle86_1": 476,
    "Rectangle86_2": 422,
    "Rectangle86_3": 494,
    "Rectangle86_4": 439,
    "Rectangle86_5": 512,
    "Rectangle87": 408,
    "Rectangle87_1": 480,
    "Rectangle87_2": 425,
    "Rectangle87_3": 498,
    "Rectangle87_4": 442,
    "Rectangle87_5": 515,
    "Rectangle89": 410,
    "Rectangle89_1": 482,
    "Rectangle89_2": 427,
    "Rectangle89_3": 500,
    "Rectangle89_4": 444,
    "Rectangle89_5": 517,
    "Rectangle9": 17,
    "ReporteRGBcolorCrystal": 57,
    "Separator2_1": 307,
    "Subtitle3_1": 190,
    "Subtitle3_2": 191,
    "Subtitle3_3": 192,
    "Subtitle3_4": 193,
    "TarjetaAlternativa": 330,
    "Test_7F478737223C4B69": 2,
    "TextInput1": 157,
    "TextInput1_1": 294,
    "TextInput1_10": 103,
    "TextInput1_2": 158,
    "TextInput1_3": 159,
    "TextInput1_4": 160,
    "TextInput1_6": 216,
    "TextInput1_7": 60,
    "TextInput1_8": 367,
    "TextInput1_9": 290,
    "TextInput2": 361,
    "TextInputB": 240,
    "TextInputG": 246,
    "TextInputR": 245,
    "TextInputReporteRGB1": 209,
    "TextoEtiquetaCodigocolor_1": 51,
    "TextoEtiquetaCodigoSAP": 207,
    "TextoEtiquetacolorCrystal": 205,
    "TextoEtiquetaNomColor": 203,
    "TextoEtiquetaPantone": 201,
    "TextoEtiquetaReporte": 208,
    "TextoEtiquetaReporte_1": 56,
    "Title2_2": 311,
    "Vector11": 407,
    "Vector11_1": 479
  },
  "DoesTestStepsMetadataExist": true,
  "FunctionParamsInvariantScripts": {},
  "FunctionParamsInvariantScriptsOnInstances": {},
  "HeaderLastSavedDateTimeUTC": "09/28/2023 19:01:02",
  "IsLegacyComponentAllowGlobalScopeCase": false,
  "LocalConnectionIDReferences": {
    "057862e6-9199-4fb8-bf78-3a96d9101551": "\"/providers/microsoft.powerapps/apis/shared_logicflows/connections/3fd42788-2207-44a9-ab2f-9e4cc30f56b4\"",
    "0bb9a89e-775e-4e7d-8303-94a5c4d38980": "\"/providers/microsoft.powerapps/apis/shared_logicflows/connections/2d2fe9cb-f2c2-4146-bbf6-d74732ce6f26\"",
    "1978edba-129a-4788-ac84-95c33de78f45": "\"/providers/microsoft.powerapps/apis/shared_sharepointonline/connections/98c8019d8ab848e18e465ae10ed14df4\"",
    "5397bef3-3a93-4303-b144-6bd2d3016aae": "\"/providers/microsoft.powerapps/apis/shared_office365users/connections/f3e893222988470389fb1440c20e0f35\"",
    "65840e2b-bc30-4d54-af6d-d8d494a863d3": "\"/providers/microsoft.powerapps/apis/shared_logicflows/connections/a18c18f232c54c1f892f21ae7ba8843c-0bc5efd839285d2e\"",
    "7df666c6-7d79-4d58-b33b-d82d977c2d79": "\"/providers/microsoft.powerapps/apis/shared_logicflows/connections/c2c0d4cb-fbc7-4683-85b8-2c30f3fcdbb4\"",
    "b6965406-cef4-4463-b637-dee95013238d": "\"/providers/microsoft.powerapps/apis/shared_office365/connections/bde3c200c901430693eced529863bb46\"",
    "edc77e13-1f26-48be-8b03-e8764365b744": "\"/providers/microsoft.powerapps/apis/shared_logicflows/connections/3472c5c8efccbc6d0b5058a7e8e76615-0bc5efd839285d2e\""
  },
  "LocalDatabaseReferencesAsEmpty": false,
  "LocalResourceFileNames": {
    "alert-circle": "0001.png",
    "charla": "0003.png",
    "charla (1)": "0002.png",
    "cuota": "0004.png",
    "image13189": "0005.png",
    "image13191": "0006.png",
    "image13193": "0007.png",
    "image13214": "0008.png",
    "image13215": "0009.png",
    "image13216": "0010.png",
    "intercambiar": "0013.png",
    "intercambiar (1)": "0011.png",
    "intercambiar (2)": "0012.png",
    "MicrosoftTeams-image (1)": "0014.png",
    "MicrosoftTeams-image (1)_1": "0015.png",
    "MicrosoftTeams-image (2)": "0017.png",
    "MicrosoftTeams-image (2) 1colorapp": "0016.png",
    "MicrosoftTeams-image (2)_1": "0018.png",
    "MicrosoftTeams-image (4)": "0019.png",
    "VAyR": "0020.gif",
    "Vector": "0026.png",
    "Vector (1)": "0021.png",
    "Vector (2)": "0022.png",
    "Vector (3)": "0023.png",
    "Vector (4)": "0024.png",
    "Vector (5)": "0025.png"
  },
  "LocalResourceRootPaths": {
    "alert-circle": "https://docserverpwaprodwus.blob.core.windows.net/113aae08-916f-48d6-bfca-93ef8d79083f-1/resource/Assets0Images00001.png?sv=2018-03-28&sr=b&sig=8hcHyhQjT24xSeekMNZ1TxEbwRxroGZc8WsKsWoxJdI%3D&spr=https&se=2023-09-29T17%3A09%3A52Z&sp=r",
    "charla": "https://docserverpwaprodwus.blob.core.windows.net/113aae08-916f-48d6-bfca-93ef8d79083f-1/resource/Assets0Images00003.png?sv=2018-03-28&sr=b&sig=MsYmGybE5D9ITEdRPaCUKoRjanGuX%2BXhzh%2BqRiP12ZE%3D&spr=https&se=2023-09-29T17%3A09%3A52Z&sp=r",
    "charla (1)": "https://docserverpwaprodwus.blob.core.windows.net/113aae08-916f-48d6-bfca-93ef8d79083f-1/resource/Assets0Images00002.png?sv=2018-03-28&sr=b&sig=bt0abJxZJrH0XGpop2JXQe5TZGe1vusyUX8aOzWeorU%3D&spr=https&se=2023-09-29T17%3A09%3A52Z&sp=r",
    "cuota": "https://docserverpwaprodwus.blob.core.windows.net/113aae08-916f-48d6-bfca-93ef8d79083f-1/resource/Assets0Images00004.png?sv=2018-03-28&sr=b&sig=Ud%2FlmBP2rSc1lqRW%2BbTNiInVFQlZHUGMOD8J9%2F%2Fqe64%3D&spr=https&se=2023-09-29T17%3A09%3A52Z&sp=r",
    "image13189": "https://docserverpwaprodwus.blob.core.windows.net/113aae08-916f-48d6-bfca-93ef8d79083f-1/resource/Assets0Images00005.png?sv=2018-03-28&sr=b&sig=Q2XtKtk3Mq4X19EaVjG6h9RgGDSy%2BbC82hGBrCrULj4%3D&spr=https&se=2023-09-29T17%3A09%3A52Z&sp=r",
    "image13191": "https://docserverpwaprodwus.blob.core.windows.net/113aae08-916f-48d6-bfca-93ef8d79083f-1/resource/Assets0Images00006.png?sv=2018-03-28&sr=b&sig=luIAL2XpzipG7JvlmRan6mOlNHHsORdBgEvmxHdipac%3D&spr=https&se=2023-09-29T17%3A09%3A52Z&sp=r",
    "image13193": "https://docserverpwaprodwus.blob.core.windows.net/113aae08-916f-48d6-bfca-93ef8d79083f-1/resource/Assets0Images00007.png?sv=2018-03-28&sr=b&sig=BDNxh3IKvLLiusniPmBjx2o0vqHM39fQP8Kse%2FptktQ%3D&spr=https&se=2023-09-29T17%3A09%3A52Z&sp=r",
    "image13214": "https://docserverpwaprodwus.blob.core.windows.net/113aae08-916f-48d6-bfca-93ef8d79083f-1/resource/Assets0Images00008.png?sv=2018-03-28&sr=b&sig=gXUJ8D65Et4YiPTE5lMBn2lW98BZbTeE6iRTsjSuF4I%3D&spr=https&se=2023-09-29T17%3A09%3A52Z&sp=r",
    "image13215": "https://docserverpwaprodwus.blob.core.windows.net/113aae08-916f-48d6-bfca-93ef8d79083f-1/resource/Assets0Images00009.png?sv=2018-03-28&sr=b&sig=s68R2Rw2lm8Hz6K9dK3Nqq4cgA4Su6WywcBv9KWcXgs%3D&spr=https&se=2023-09-29T17%3A09%3A52Z&sp=r",
    "image13216": "https://docserverpwaprodwus.blob.core.windows.net/113aae08-916f-48d6-bfca-93ef8d79083f-1/resource/Assets0Images00010.png?sv=2018-03-28&sr=b&sig=3zcAba3AR5FBKazfUt0kqX5uCADHnL1IwvSBqef6RVI%3D&spr=https&se=2023-09-29T17%3A09%3A52Z&sp=r",
    "intercambiar": "https://docserverpwaprodwus.blob.core.windows.net/113aae08-916f-48d6-bfca-93ef8d79083f-1/resource/Assets0Images00013.png?sv=2018-03-28&sr=b&sig=IylGr6qgYTusUZuzMDMA2CRVT2i8zRUf%2Bu29Wt5jPeU%3D&spr=https&se=2023-09-29T17%3A09%3A52Z&sp=r",
    "intercambiar (1)": "https://docserverpwaprodwus.blob.core.windows.net/113aae08-916f-48d6-bfca-93ef8d79083f-1/resource/Assets0Images00011.png?sv=2018-03-28&sr=b&sig=e39DYD4I%2BshkMLwuAeOyvMLIom5w5pW8XGqSGE1vnec%3D&spr=https&se=2023-09-29T17%3A09%3A52Z&sp=r",
    "intercambiar (2)": "https://docserverpwaprodwus.blob.core.windows.net/113aae08-916f-48d6-bfca-93ef8d79083f-1/resource/Assets0Images00012.png?sv=2018-03-28&sr=b&sig=9gR3i7l6LHtAll3BsOFT5gnBMQ8E4Q%2BfTu1jKHAS5Ww%3D&spr=https&se=2023-09-29T17%3A09%3A52Z&sp=r",
    "MicrosoftTeams-image (1)": "https://docserverpwaprodwus.blob.core.windows.net/113aae08-916f-48d6-bfca-93ef8d79083f-1/resource/Assets0Images00014.png?sv=2018-03-28&sr=b&sig=3WO0aCjnyRlrh2KDgpdKNITs1mQbrywOFdPidFdkLNk%3D&spr=https&se=2023-09-29T17%3A09%3A52Z&sp=r",
    "MicrosoftTeams-image (1)_1": "https://docserverpwaprodwus.blob.core.windows.net/113aae08-916f-48d6-bfca-93ef8d79083f-1/resource/Assets0Images00015.png?sv=2018-03-28&sr=b&sig=shXL3xp6Nf2CKf51edfI6xMnejZIjoUZwGbDHPwJizw%3D&spr=https&se=2023-09-29T17%3A09%3A52Z&sp=r",
    "MicrosoftTeams-image (2)": "https://docserverpwaprodwus.blob.core.windows.net/113aae08-916f-48d6-bfca-93ef8d79083f-1/resource/Assets0Images00017.png?sv=2018-03-28&sr=b&sig=I3QYK0N%2FlcGRetMGs%2BqyB%2BUQMBW8mgHETkiHNuT77%2BE%3D&spr=https&se=2023-09-29T17%3A09%3A52Z&sp=r",
    "MicrosoftTeams-image (2) 1colorapp": "https://docserverpwaprodwus.blob.core.windows.net/113aae08-916f-48d6-bfca-93ef8d79083f-1/resource/Assets0Images00016.png?sv=2018-03-28&sr=b&sig=AFpn27GQ4DNj8dsVYcYdDneSypUjcLdOOOqmGnqC6mM%3D&spr=https&se=2023-09-29T17%3A09%3A52Z&sp=r",
    "MicrosoftTeams-image (2)_1": "https://docserverpwaprodwus.blob.core.windows.net/113aae08-916f-48d6-bfca-93ef8d79083f-1/resource/Assets0Images00018.png?sv=2018-03-28&sr=b&sig=eEL5gCEiP82EdUjdGIF9gJbNCVzs9RgtxjUGia%2FOsmA%3D&spr=https&se=2023-09-29T17%3A09%3A52Z&sp=r",
    "MicrosoftTeams-image (4)": "https://docserverpwaprodwus.blob.core.windows.net/113aae08-916f-48d6-bfca-93ef8d79083f-1/resource/Assets0Images00019.png?sv=2018-03-28&sr=b&sig=yezdenCGf3g4pbKUGTOaLjR4icsVHNYPDAp4Wx5yQiI%3D&spr=https&se=2023-09-29T17%3A09%3A52Z&sp=r",
    "VAyR": "https://docserverpwaprodwus.blob.core.windows.net/113aae08-916f-48d6-bfca-93ef8d79083f-1/resource/Assets0Images00020.gif?sv=2018-03-28&sr=b&sig=8JB9%2F2%2FIG3MYDw93cQk3yZ4C7mr%2B9Rfu8eHLQIDuEvE%3D&spr=https&se=2023-09-29T17%3A09%3A52Z&sp=r",
    "Vector": "https://docserverpwaprodwus.blob.core.windows.net/113aae08-916f-48d6-bfca-93ef8d79083f-1/resource/Assets0Images00026.png?sv=2018-03-28&sr=b&sig=Qs0OUQioUzYjOFtwy9CySjiJFwgdMDLeukj2zNUwKTs%3D&spr=https&se=2023-09-29T17%3A09%3A52Z&sp=r",
    "Vector (1)": "https://docserverpwaprodwus.blob.core.windows.net/113aae08-916f-48d6-bfca-93ef8d79083f-1/resource/Assets0Images00021.png?sv=2018-03-28&sr=b&sig=%2Fw9NprBZ3IxRpoI0w791ZJqSWqTUKcy4XDHvAACuT0w%3D&spr=https&se=2023-09-29T17%3A09%3A52Z&sp=r",
    "Vector (2)": "https://docserverpwaprodwus.blob.core.windows.net/113aae08-916f-48d6-bfca-93ef8d79083f-1/resource/Assets0Images00022.png?sv=2018-03-28&sr=b&sig=Y8b90GZnzLHO3G6Fp%2BCz3VYMRX6IUkQ4otPgteGF%2BTo%3D&spr=https&se=2023-09-29T17%3A09%3A52Z&sp=r",
    "Vector (3)": "https://docserverpwaprodwus.blob.core.windows.net/113aae08-916f-48d6-bfca-93ef8d79083f-1/resource/Assets0Images00023.png?sv=2018-03-28&sr=b&sig=QgLFfe%2BbqdZiw3zACM%2BOzEo2YZUMrNLAhnhQjN8Fj6w%3D&spr=https&se=2023-09-29T17%3A09%3A52Z&sp=r",
    "Vector (4)": "https://docserverpwaprodwus.blob.core.windows.net/113aae08-916f-48d6-bfca-93ef8d79083f-1/resource/Assets0Images00024.png?sv=2018-03-28&sr=b&sig=vC2bznzMSecPqVrsQ70gERV3rPpfwzuuH5hCWrqC0oI%3D&spr=https&se=2023-09-29T17%3A09%3A52Z&sp=r",
    "Vector (5)": "https://docserverpwaprodwus.blob.core.windows.net/113aae08-916f-48d6-bfca-93ef8d79083f-1/resource/Assets0Images00025.png?sv=2018-03-28&sr=b&sig=J8qOKkaPKwuh1N3B38uX9AsPe7T5AIGOSnDJxVPzcAA%3D&spr=https&se=2023-09-29T17%3A09%3A52Z&sp=r"
  },
  "OldLogoFileName": "logo.jpg",
  "OrderComponentMetadata": {},
  "OrderComponentTemplate": {},
  "OrderDataSource": {
    "adminUsers": 19,
    "afColorCalceteriaDev": 0,
    "COAPP_DEV_EXCEL_ENEAS_DOWNLOAD": 1,
    "COAPP_DEV_SUGERENCIA_VANISADOS": 2,
    "COAPP_PRD_PDF_2": 3,
    "coleccionAlternativa": 20,
    "colorCalceteriaDev": 7,
    "coloresUnicosDev": 8,
    "Colorrgb": 21,
    "ComboBoxSample": 9,
    "CustomGallerySample": 10,
    "DatosUsoColorApp": 11,
    "DropDownSample": 12,
    "Flujo_Excel_Horarios": 4,
    "gall": 22,
    "gallVanisadoUnico": 23,
    "GestionVanisadosDEV": 13,
    "ListboxSample": 14,
    "MyCollection": 24,
    "Office365Outlook": 5,
    "pantoneRgbFull_1Dev": 15,
    "ReporteDeErrores": 16,
    "Roles_Dev": 17,
    "SugerenciaVanisados": 18,
    "UsuariosdeOffice365": 6
  },
  "OrderGroupControls": {},
  "OrderPcfTemplate": {},
  "OrderTemplate": {},
  "OrderXMLTemplate": {
    "button": 6,
    "checkbox": 11,
    "circle": 9,
    "combobox": 10,
    "dropdown": 8,
    "gallery": 4,
    "groupContainer": 0,
    "icon": 5,
    "image": 2,
    "label": 3,
    "rectangle": 1,
    "text": 7
  },
  "OverridablePropertiesEntry": {
    "App": {},
    "bebebc1e-b3b2-4049-abe0-9d6a81d63330": {},
    "Button1": {},
    "Button1_10": {},
    "Button1_11": {},
    "Button1_12": {},
    "Button1_13": {},
    "Button1_14": {},
    "Button1_15": {},
    "Button1_16": {},
    "Button1_17": {},
    "Button1_18": {},
    "Button1_19": {},
    "Button1_20": {},
    "Button1_21": {},
    "Button1_5": {},
    "Button1_8": {},
    "Button1_9": {},
    "Button11_1": {},
    "Button11_5": {},
    "Button11_6": {},
    "Button11_7": {},
    "Button11_8": {},
    "Button13_4": {},
    "Button13_5": {},
    "Button13_6": {},
    "Button13_7": {},
    "Button13_8": {},
    "Button2": {},
    "Button3": {},
    "Button3_1": {},
    "Button3_2": {},
    "Button3_3": {},
    "Button3_4": {},
    "Button3_5": {},
    "Button3_6": {},
    "Button3_7": {},
    "Button5": {},
    "Button5_1": {},
    "Button6": {},
    "Button6_1": {},
    "Button6_4": {},
    "Button6_6": {},
    "Button6_7": {},
    "Button6_8": {},
    "Button6_9": {},
    "Button7": {},
    "Button8": {},
    "Button9": {},
    "Button9_1": {},
    "Button9_10": {},
    "Button9_11": {},
    "Button9_12": {},
    "Button9_13": {},
    "Button9_14": {},
    "Button9_15": {},
    "Button9_16": {},
    "Button9_17": {},
    "Button9_2": {},
    "Button9_3": {},
    "Button9_4": {},
    "Button9_5": {},
    "Button9_7": {},
    "Button9_8": {},
    "Button9_9": {},
    "ButtonGuardar_1": {},
    "ButtonGuardar1": {},
    "CdigoCrystal_11": {},
    "CdigoCrystal_12": {},
    "CdigoCrystal_13": {},
    "CdigoCrystal_17": {},
    "CdigoCrystal_4": {},
    "CdigoCrystal_5": {},
    "CdigoCrystal_6": {},
    "CdigoCrystal_7": {},
    "CdigoCrystal_8": {},
    "CdigoCrystal_9": {},
    "CdigoCrystal9": {},
    "CdigoMaterial": {},
    "Checkbox4": {},
    "Circle1": {},
    "Circle2_1": {},
    "Circle2_2": {},
    "Codigo_rgb": {},
    "codigoInput": {},
    "color_Crystal": {},
    "ColorCrystal": {},
    "ColorCrystal_1": {},
    "ColorCrystal_2": {},
    "Colores_Crystal": {},
    "ColoresSeleccionados": {},
    "colorInput": {},
    "ComboBox1": {},
    "ComboBox1_1": {},
    "ComboBox2": {},
    "ComboBox2_1": {},
    "ComboBox2_2": {},
    "ComboBox3": {},
    "ComboBox4": {},
    "ConAlerta44/2": {},
    "ConAlerta44/2_1": {},
    "ConAlerta78/2": {},
    "ConAlerta78/2_1": {},
    "ConAlertaElastico": {},
    "ConAlertaElastico_1": {},
    "ConAlertaLycra": {},
    "ConAlertaLycra_1": {},
    "Container_barraNavegacionColoresCrystal": {},
    "Container_barraNavegacionPantone": {},
    "Container_barraNavegacionRGB_Eneas": {},
    "Container_barraNavegacionvanisados": {},
    "Container_barraNavegacionVanisados": {},
    "Container_Botton": {},
    "Container_codigoRGB": {},
    "Container_cuadro": {},
    "Container_Filtros": {},
    "Container_FiltrosColorcrystal": {},
    "Container_FiltrosVanisados": {},
    "Container_Gallery2": {},
    "Container_GestionVanizados": {},
    "Container_pop_up": {},
    "Container_Popup": {},
    "Container1": {},
    "Container12": {},
    "Container2_1": {},
    "Container2_2": {},
    "Container2_3": {},
    "Container2_4": {},
    "Container2_5": {},
    "Container22": {},
    "Container3": {},
    "Container3_1": {},
    "Container6": {},
    "Containerbarratabla": {},
    "ContainerBarratabla": {},
    "ContainerbarratablaGallery5": {},
    "ContainerBase": {},
    "containerBaseCrystal": {},
    "ContainerBotones": {},
    "ContainerBotton": {},
    "ContainercCoTargeta": {},
    "ContainerColorSeleccion": {},
    "ContainercomboBox": {},
    "ContainerComentarios": {},
    "ContainerCuadro": {},
    "ContainerDaToscolor_1": {},
    "ContainerDatoscolor_2": {},
    "ContainerDaToscolor_2": {},
    "ContainerDatoscolor_3": {},
    "ContainerDatoscolor_4": {},
    "ContainerDatoscolor_5": {},
    "ContainerDatoscolor_6": {},
    "ContainerDatoscolor_7": {},
    "ContaineRectangulo": {},
    "Containerinputtabla": {},
    "ContainerLandingPage": {},
    "ContainerLogo": {},
    "ContainerLogo_1": {},
    "ContainerLogo_2": {},
    "ContainerLogo_3": {},
    "ContainerLogo_4": {},
    "ContainerLogo_5": {},
    "ContainerPadre": {},
    "ContainerRecomendado": {},
    "ContainerRGB": {},
    "ContainerRoles": {},
    "ContainerSuge_vanisado": {},
    "ContainerSugerencia": {},
    "ContainertarColor": {},
    "Containertarjetapequeña": {},
    "ContainerTarjetas": {},
    "ContainerTarjetasGran": {},
    "ContaITarjeta": {},
    "Contenedor": {},
    "ContenedorBase": {},
    "ContenedorPopPapSugerencia": {},
    "contenedorTarjetaElastico": {},
    "contenedorTarjetaElastico_1": {},
    "contenedorTarjetaLycra": {},
    "contenedorTarjetaLycra_1": {},
    "contenedortarjetaVani.44/2": {},
    "contenedortarjetaVani.44/2_1": {},
    "contenedortarjetaVani.78/2": {},
    "contenedortarjetaVani.78/2_1": {},
    "ConteneTarjeR_RGB": {},
    "Datosdelcolor": {},
    "Datosdelcolor_1": {},
    "Datosdelcolor_2": {},
    "Datosdelcolor_3": {},
    "Datosdelcolor_4": {},
    "Datosdelcolor_5": {},
    "Datosdelcolor_6": {},
    "Datosdelcolor_7": {},
    "Datosdelcolor9": {},
    "DescargarPDF": {},
    "Descripcin": {},
    "Dropdown1": {},
    "Dropdown1_1": {},
    "Dropdown1_2": {},
    "Dropdown2": {},
    "DropdownColores": {},
    "DropdownMaterial": {},
    "Elasticoexpuesto": {},
    "Elasticoexpuesto_1": {},
    "Elasticoexpuesto_2": {},
    "Elasticoexpuesto_6": {},
    "Elasticoexpuesto_7": {},
    "EtiquetaCodigoSAP": {},
    "EtiquetaDescripcion": {},
    "EtiquetaTextoCodigoSAP": {},
    "EtiquetaTextoColorCrystal": {},
    "EtiquetaTextoNombreColor": {},
    "EtiquetaTextopantone": {},
    "fed87c5f-ccd6-47f6-b984-bfaff76af83a": {},
    "Galeria_Alternativa": {},
    "Galeria_Datos": {},
    "Gallery1": {},
    "Gallery2": {},
    "Gallery3": {},
    "Gallery3_1": {},
    "Gallery4": {},
    "Gallery5": {},
    "GalleryRGB": {},
    "galleryTemplate1": {},
    "galleryTemplate2": {},
    "galleryTemplate3": {},
    "galleryTemplate3_1": {},
    "galleryTemplate3_2": {},
    "galleryTemplate4": {},
    "galleryTemplate5": {},
    "galleryTemplate5_1": {},
    "galleryTemplate5_2": {},
    "Host": {},
    "Icon1": {},
    "Icon1_1": {},
    "Icon1_3": {},
    "Icon1_4": {},
    "Icon1_5": {},
    "Icon1_6": {},
    "Icon1_7": {},
    "Icon10": {},
    "Icon10_1": {},
    "Icon10_10": {},
    "Icon10_11": {},
    "Icon10_12": {},
    "Icon10_13": {},
    "Icon10_14": {},
    "Icon10_15": {},
    "Icon10_16": {},
    "Icon10_2": {},
    "Icon10_3": {},
    "Icon10_4": {},
    "Icon10_5": {},
    "Icon10_6": {},
    "Icon10_7": {},
    "Icon10_8": {},
    "Icon10_9": {},
    "Icon11": {},
    "Icon12": {},
    "Icon12_1": {},
    "Icon12_2": {},
    "Icon12_3": {},
    "Icon12_4": {},
    "Icon13": {},
    "Icon17": {},
    "Icon2": {},
    "Icon3": {},
    "Icon4": {},
    "Icon5": {},
    "Icon6": {},
    "Icon7": {},
    "Icon8": {},
    "Icon9": {},
    "IconCerrarPopup": {},
    "IconCerrarPopup_1": {},
    "Image1": {},
    "Image1_10": {},
    "Image1_5": {},
    "Image1_6": {},
    "Image1_7": {},
    "Image1_8": {},
    "Image1_9": {},
    "Image10": {},
    "Image11": {},
    "Image12": {},
    "Image13": {},
    "Image14": {},
    "Image15": {},
    "Image16": {},
    "Image2": {},
    "Image22": {},
    "Image3": {},
    "Image3_2": {},
    "Image3_3": {},
    "Image3_4": {},
    "Image3_5": {},
    "Image3_6": {},
    "Image3_7": {},
    "Image3_8": {},
    "Image3_9": {},
    "Image4": {},
    "Image5": {},
    "Image5_1": {},
    "Image5_2": {},
    "Image5_3": {},
    "Image5_4": {},
    "Image5_5": {},
    "Image6": {},
    "Image7": {},
    "Image9": {},
    "Imagen_de_Carga": {},
    "Label1": {},
    "Label1_1": {},
    "Label1_2": {},
    "Label1_3": {},
    "Label1_4": {},
    "Label1_5": {},
    "Label1_6": {},
    "Label1_7": {},
    "Label1_8": {},
    "Label10": {},
    "Label10_1": {},
    "Label10_2": {},
    "Label11": {},
    "Label12": {},
    "Label13": {},
    "Label14": {},
    "Label14_1": {},
    "Label15": {},
    "Label16": {},
    "Label17": {},
    "Label18": {},
    "Label18_1": {},
    "Label18_2": {},
    "Label18_3": {},
    "Label18_4": {},
    "Label18_5": {},
    "Label19": {},
    "Label2": {},
    "Label2_1": {},
    "Label2_2": {},
    "Label2_3": {},
    "Label2_4": {},
    "Label2_5": {},
    "Label20": {},
    "Label21": {},
    "Label22": {},
    "Label22_1": {},
    "Label22_2": {},
    "Label22_3": {},
    "Label22_4": {},
    "Label22_5": {},
    "Label22_6": {},
    "Label22_7": {},
    "Label23": {},
    "Label25": {},
    "Label25_1": {},
    "Label25_10": {},
    "Label25_11": {},
    "Label25_2": {},
    "Label25_3": {},
    "Label25_4": {},
    "Label25_5": {},
    "Label25_6": {},
    "Label25_7": {},
    "Label25_8": {},
    "Label25_9": {},
    "Label3": {},
    "Label3_1": {},
    "Label3_10": {},
    "Label3_11": {},
    "Label3_12": {},
    "Label3_13": {},
    "Label3_2": {},
    "Label3_3": {},
    "Label3_4": {},
    "Label3_5": {},
    "Label3_6": {},
    "Label3_7": {},
    "Label3_8": {},
    "Label3_9": {},
    "Label4": {},
    "Label4_1": {},
    "Label4_2": {},
    "Label4_3": {},
    "Label4_4": {},
    "Label4_5": {},
    "Label4_6": {},
    "Label4_7": {},
    "Label5": {},
    "Label5_1": {},
    "Label5_2": {},
    "Label5_3": {},
    "Label5_4": {},
    "Label5_5": {},
    "Label5_6": {},
    "Label5_7": {},
    "Label6": {},
    "Label6_3": {},
    "Label6_4": {},
    "Label6_5": {},
    "Label6_6": {},
    "Label6_7": {},
    "Label6_8": {},
    "Label7": {},
    "Label7_1": {},
    "Label7_2": {},
    "Label8": {},
    "Label8_1": {},
    "Label8_5": {},
    "Label8_7": {},
    "Label9": {},
    "Label9_1": {},
    "Label9_2": {},
    "Label9_3": {},
    "Label9_4": {},
    "Label9_5": {},
    "Label9_6": {},
    "Label9_7": {},
    "Label9_8": {},
    "LabelCapturaRGB_NO_BORRAR": {},
    "labelCoColor": {},
    "LabelCodigoSap": {},
    "LabelDescripcion": {},
    "LabelNombre": {},
    "materiaPrima": {},
    "materiaPrima_1": {},
    "Materiaprimaprincipal_1": {},
    "Materiaprimaprincipal_2": {},
    "Materiaprimaprincipal1": {},
    "Mssimilar1_7": {},
    "Mssimilar1_8": {},
    "Mssimilar4": {},
    "Nombredecolor": {},
    "Pantalla_GestionVanisados": {},
    "Pantalla_Pantone": {},
    "Pantalla_RGB_ENEAS": {},
    "Pantalla_Vanisados": {},
    "Pantonecdigo": {},
    "Pantonecdigo_1": {},
    "Rectangle1": {},
    "Rectangle1_2": {},
    "Rectangle1_3": {},
    "Rectangle1_4": {},
    "Rectangle1_5": {},
    "Rectangle1_6": {},
    "Rectangle10_1": {},
    "Rectangle10_2": {},
    "Rectangle10_3": {},
    "Rectangle10_4": {},
    "Rectangle11_2": {},
    "Rectangle12": {},
    "Rectangle15": {},
    "Rectangle15_1": {},
    "Rectangle15_2": {},
    "Rectangle15_3": {},
    "Rectangle15_5": {},
    "Rectangle151": {},
    "Rectangle16": {},
    "Rectangle16_1": {},
    "Rectangle16_3": {},
    "Rectangle161": {},
    "Rectangle18": {},
    "Rectangle2": {},
    "Rectangle211": {},
    "Rectangle211_1": {},
    "Rectangle3": {},
    "Rectangle4": {},
    "Rectangle40": {},
    "Rectangle5": {},
    "Rectangle5_1": {},
    "Rectangle6": {},
    "Rectangle6_2": {},
    "Rectangle7": {},
    "Rectangle73": {},
    "Rectangle73_1": {},
    "Rectangle73_3": {},
    "Rectangle8": {},
    "Rectangle86": {},
    "Rectangle86_1": {},
    "Rectangle86_2": {},
    "Rectangle86_3": {},
    "Rectangle86_4": {},
    "Rectangle86_5": {},
    "Rectangle87": {},
    "Rectangle87_1": {},
    "Rectangle87_2": {},
    "Rectangle87_3": {},
    "Rectangle87_4": {},
    "Rectangle87_5": {},
    "Rectangle89": {},
    "Rectangle89_1": {},
    "Rectangle89_2": {},
    "Rectangle89_3": {},
    "Rectangle89_4": {},
    "Rectangle89_5": {},
    "Rectangle9": {},
    "ReporteRGBcolorCrystal": {},
    "Separator2_1": {},
    "Subtitle3_1": {},
    "Subtitle3_2": {},
    "Subtitle3_3": {},
    "Subtitle3_4": {},
    "TarjetaAlternativa": {},
    "Test_7F478737223C4B69": {},
    "TextInput1": {},
    "TextInput1_1": {},
    "TextInput1_10": {},
    "TextInput1_2": {},
    "TextInput1_3": {},
    "TextInput1_4": {},
    "TextInput1_6": {},
    "TextInput1_7": {},
    "TextInput1_8": {},
    "TextInput1_9": {},
    "TextInput2": {},
    "TextInputB": {},
    "TextInputG": {},
    "TextInputR": {},
    "TextInputReporteRGB1": {},
    "TextoEtiquetaCodigocolor_1": {},
    "TextoEtiquetaCodigoSAP": {},
    "TextoEtiquetacolorCrystal": {},
    "TextoEtiquetaNomColor": {},
    "TextoEtiquetaPantone": {},
    "TextoEtiquetaReporte": {},
    "TextoEtiquetaReporte_1": {},
    "Title2_2": {},
    "Vector11": {},
    "Vector11_1": {}
  },
  "PCFDynamicSchemaForIRRetrievalEntry": {},
  "PCFTemplateEntry": {},
  "PublishOrderIndices": {
    "App": 0,
    "bebebc1e-b3b2-4049-abe0-9d6a81d63330": 530,
    "Button1": 144,
    "Button1_10": 379,
    "Button1_11": 435,
    "Button1_12": 440,
    "Button1_13": 436,
    "Button1_14": 166,
    "Button1_15": 441,
    "Button1_16": 380,
    "Button1_17": 167,
    "Button1_18": 112,
    "Button1_19": 113,
    "Button1_20": 28,
    "Button1_21": 31,
    "Button1_5": 219,
    "Button1_8": 419,
    "Button1_9": 420,
    "Button11_1": 423,
    "Button11_5": 383,
    "Button11_6": 170,
    "Button11_7": 116,
    "Button11_8": 34,
    "Button13_4": 422,
    "Button13_5": 382,
    "Button13_6": 169,
    "Button13_7": 115,
    "Button13_8": 33,
    "Button2": 51,
    "Button3": 231,
    "Button3_1": 303,
    "Button3_2": 248,
    "Button3_3": 267,
    "Button3_4": 284,
    "Button3_5": 320,
    "Button3_6": 340,
    "Button3_7": 357,
    "Button5": 486,
    "Button5_1": 487,
    "Button6": 208,
    "Button6_1": 491,
    "Button6_4": 421,
    "Button6_6": 381,
    "Button6_7": 168,
    "Button6_8": 114,
    "Button6_9": 32,
    "Button7": 76,
    "Button8": 411,
    "Button9": 279,
    "Button9_1": 241,
    "Button9_10": 316,
    "Button9_11": 331,
    "Button9_12": 334,
    "Button9_13": 338,
    "Button9_14": 349,
    "Button9_15": 352,
    "Button9_16": 366,
    "Button9_17": 369,
    "Button9_2": 262,
    "Button9_3": 296,
    "Button9_4": 244,
    "Button9_5": 259,
    "Button9_7": 276,
    "Button9_8": 293,
    "Button9_9": 313,
    "ButtonGuardar_1": 130,
    "ButtonGuardar1": 18,
    "CdigoCrystal_11": 290,
    "CdigoCrystal_12": 363,
    "CdigoCrystal_13": 184,
    "CdigoCrystal_17": 185,
    "CdigoCrystal_4": 238,
    "CdigoCrystal_5": 256,
    "CdigoCrystal_6": 273,
    "CdigoCrystal_7": 310,
    "CdigoCrystal_8": 328,
    "CdigoCrystal_9": 346,
    "CdigoCrystal9": 63,
    "CdigoMaterial": 67,
    "Checkbox4": 57,
    "Circle1": 407,
    "Circle2_1": 432,
    "Circle2_2": 438,
    "Codigo_rgb": 409,
    "codigoInput": 141,
    "color_Crystal": 41,
    "ColorCrystal": 217,
    "ColorCrystal_1": 136,
    "ColorCrystal_2": 137,
    "Colores_Crystal": 31,
    "ColoresSeleccionados": 3,
    "colorInput": 140,
    "ComboBox1": 47,
    "ComboBox1_1": 480,
    "ComboBox2": 218,
    "ComboBox2_1": 48,
    "ComboBox2_2": 467,
    "ComboBox3": 498,
    "ComboBox4": 490,
    "ConAlerta44/2": 258,
    "ConAlerta44/2_1": 330,
    "ConAlerta78/2": 240,
    "ConAlerta78/2_1": 312,
    "ConAlertaElastico": 275,
    "ConAlertaElastico_1": 348,
    "ConAlertaLycra": 292,
    "ConAlertaLycra_1": 365,
    "Container_barraNavegacionColoresCrystal": 105,
    "Container_barraNavegacionPantone": 23,
    "Container_barraNavegacionRGB_Eneas": 372,
    "Container_barraNavegacionvanisados": 412,
    "Container_barraNavegacionVanisados": 159,
    "Container_Botton": 75,
    "Container_codigoRGB": 390,
    "Container_cuadro": 448,
    "Container_Filtros": 36,
    "Container_FiltrosColorcrystal": 135,
    "Container_FiltrosVanisados": 213,
    "Container_Gallery2": 52,
    "Container_GestionVanizados": 462,
    "Container_pop_up": 1,
    "Container_Popup": 119,
    "Container1": 385,
    "Container12": 61,
    "Container2_1": 19,
    "Container2_2": 131,
    "Container2_3": 209,
    "Container2_4": 386,
    "Container2_5": 426,
    "Container22": 403,
    "Container3": 494,
    "Container3_1": 497,
    "Container6": 180,
    "Containerbarratabla": 468,
    "ContainerBarratabla": 396,
    "ContainerbarratablaGallery5": 220,
    "ContainerBase": 189,
    "containerBaseCrystal": 118,
    "ContainerBotones": 485,
    "ContainerBotton": 410,
    "ContainercCoTargeta": 37,
    "ContainerColorSeleccion": 78,
    "ContainercomboBox": 463,
    "ContainerComentarios": 425,
    "ContainerCuadro": 465,
    "ContainerDaToscolor_1": 286,
    "ContainerDatoscolor_2": 269,
    "ContainerDaToscolor_2": 359,
    "ContainerDatoscolor_3": 252,
    "ContainerDatoscolor_4": 234,
    "ContainerDatoscolor_5": 306,
    "ContainerDatoscolor_6": 324,
    "ContainerDatoscolor_7": 342,
    "ContaineRectangulo": 152,
    "Containerinputtabla": 475,
    "ContainerLandingPage": 431,
    "ContainerLogo": 414,
    "ContainerLogo_1": 374,
    "ContainerLogo_2": 161,
    "ContainerLogo_3": 107,
    "ContainerLogo_4": 25,
    "ContainerLogo_5": 80,
    "ContainerPadre": 86,
    "ContainerRecomendado": 190,
    "ContainerRGB": 443,
    "ContainerRoles": 488,
    "ContainerSuge_vanisado": 503,
    "ContainerSugerencia": 500,
    "ContainertarColor": 214,
    "Containertarjetapequeña": 92,
    "ContainerTarjetas": 55,
    "ContainerTarjetasGran": 87,
    "ContaITarjeta": 147,
    "Contenedor": 430,
    "ContenedorBase": 0,
    "ContenedorPopPapSugerencia": 172,
    "contenedorTarjetaElastico": 264,
    "contenedorTarjetaElastico_1": 336,
    "contenedorTarjetaLycra": 281,
    "contenedorTarjetaLycra_1": 354,
    "contenedortarjetaVani.44/2": 246,
    "contenedortarjetaVani.44/2_1": 318,
    "contenedortarjetaVani.78/2": 229,
    "contenedortarjetaVani.78/2_1": 301,
    "ConteneTarjeR_RGB": 446,
    "Datosdelcolor": 237,
    "Datosdelcolor_1": 255,
    "Datosdelcolor_2": 272,
    "Datosdelcolor_3": 309,
    "Datosdelcolor_4": 327,
    "Datosdelcolor_5": 345,
    "Datosdelcolor_6": 289,
    "Datosdelcolor_7": 362,
    "Datosdelcolor9": 66,
    "DescargarPDF": 77,
    "Descripcin": 69,
    "Dropdown1": 45,
    "Dropdown1_1": 198,
    "Dropdown1_2": 196,
    "Dropdown2": 46,
    "DropdownColores": 143,
    "DropdownMaterial": 142,
    "Elasticoexpuesto": 225,
    "Elasticoexpuesto_1": 224,
    "Elasticoexpuesto_2": 223,
    "Elasticoexpuesto_6": 226,
    "Elasticoexpuesto_7": 222,
    "EtiquetaCodigoSAP": 127,
    "EtiquetaDescripcion": 125,
    "EtiquetaTextoCodigoSAP": 10,
    "EtiquetaTextoColorCrystal": 8,
    "EtiquetaTextoNombreColor": 6,
    "EtiquetaTextopantone": 4,
    "fed87c5f-ccd6-47f6-b984-bfaff76af83a": 529,
    "Galeria_Alternativa": 299,
    "Galeria_Datos": 227,
    "Gallery1": 145,
    "Gallery2": 53,
    "Gallery3": 444,
    "Gallery3_1": 84,
    "Gallery4": 492,
    "Gallery5": 501,
    "GalleryRGB": 401,
    "galleryTemplate1": 146,
    "galleryTemplate2": 54,
    "galleryTemplate3": 445,
    "galleryTemplate3_1": 85,
    "galleryTemplate3_2": 402,
    "galleryTemplate4": 493,
    "galleryTemplate5": 502,
    "galleryTemplate5_1": 228,
    "galleryTemplate5_2": 300,
    "Host": 0,
    "Icon1": 175,
    "Icon1_1": 395,
    "Icon1_3": 22,
    "Icon1_4": 134,
    "Icon1_5": 212,
    "Icon1_6": 389,
    "Icon1_7": 429,
    "Icon10": 291,
    "Icon10_1": 274,
    "Icon10_10": 317,
    "Icon10_11": 329,
    "Icon10_12": 335,
    "Icon10_13": 347,
    "Icon10_14": 353,
    "Icon10_15": 364,
    "Icon10_16": 370,
    "Icon10_2": 257,
    "Icon10_3": 239,
    "Icon10_4": 188,
    "Icon10_5": 245,
    "Icon10_6": 263,
    "Icon10_7": 280,
    "Icon10_8": 297,
    "Icon10_9": 311,
    "Icon11": 447,
    "Icon12": 21,
    "Icon12_1": 133,
    "Icon12_2": 211,
    "Icon12_3": 388,
    "Icon12_4": 428,
    "Icon13": 90,
    "Icon17": 510,
    "Icon2": 392,
    "Icon3": 73,
    "Icon4": 104,
    "Icon5": 103,
    "Icon6": 199,
    "Icon7": 151,
    "Icon8": 511,
    "Icon9": 192,
    "IconCerrarPopup": 3,
    "IconCerrarPopup_1": 121,
    "Image1": 82,
    "Image1_10": 35,
    "Image1_5": 424,
    "Image1_6": 384,
    "Image1_7": 434,
    "Image1_8": 171,
    "Image1_9": 117,
    "Image10": 377,
    "Image11": 417,
    "Image12": 30,
    "Image13": 378,
    "Image14": 111,
    "Image15": 418,
    "Image16": 74,
    "Image2": 165,
    "Image22": 442,
    "Image3": 499,
    "Image3_2": 260,
    "Image3_3": 277,
    "Image3_4": 294,
    "Image3_5": 242,
    "Image3_6": 314,
    "Image3_7": 332,
    "Image3_8": 350,
    "Image3_9": 367,
    "Image4": 495,
    "Image5": 415,
    "Image5_1": 375,
    "Image5_2": 162,
    "Image5_3": 108,
    "Image5_4": 26,
    "Image5_5": 81,
    "Image6": 29,
    "Image7": 110,
    "Image9": 164,
    "Imagen_de_Carga": 187,
    "Label1": 150,
    "Label1_1": 156,
    "Label1_2": 158,
    "Label1_3": 464,
    "Label1_4": 471,
    "Label1_5": 472,
    "Label1_6": 473,
    "Label1_7": 470,
    "Label1_8": 474,
    "Label10": 207,
    "Label10_1": 433,
    "Label10_2": 439,
    "Label11": 15,
    "Label12": 518,
    "Label13": 14,
    "Label14": 94,
    "Label14_1": 95,
    "Label15": 39,
    "Label16": 513,
    "Label17": 512,
    "Label18": 504,
    "Label18_1": 505,
    "Label18_2": 506,
    "Label18_3": 507,
    "Label18_4": 508,
    "Label18_5": 509,
    "Label19": 16,
    "Label2": 83,
    "Label2_1": 394,
    "Label2_2": 399,
    "Label2_3": 400,
    "Label2_4": 393,
    "Label2_5": 398,
    "Label20": 65,
    "Label21": 17,
    "Label22": 96,
    "Label22_1": 101,
    "Label22_2": 97,
    "Label22_3": 98,
    "Label22_4": 100,
    "Label22_5": 99,
    "Label22_6": 102,
    "Label22_7": 89,
    "Label23": 496,
    "Label25": 450,
    "Label25_1": 451,
    "Label25_10": 457,
    "Label25_11": 460,
    "Label25_2": 459,
    "Label25_3": 454,
    "Label25_4": 455,
    "Label25_5": 458,
    "Label25_6": 461,
    "Label25_7": 452,
    "Label25_8": 456,
    "Label25_9": 453,
    "Label3": 200,
    "Label3_1": 202,
    "Label3_10": 193,
    "Label3_11": 194,
    "Label3_12": 205,
    "Label3_13": 191,
    "Label3_2": 186,
    "Label3_3": 183,
    "Label3_4": 2,
    "Label3_5": 120,
    "Label3_6": 195,
    "Label3_7": 203,
    "Label3_8": 201,
    "Label3_9": 197,
    "Label4": 243,
    "Label4_1": 315,
    "Label4_2": 261,
    "Label4_3": 278,
    "Label4_4": 295,
    "Label4_5": 333,
    "Label4_6": 351,
    "Label4_7": 368,
    "Label5": 232,
    "Label5_1": 249,
    "Label5_2": 304,
    "Label5_3": 266,
    "Label5_4": 283,
    "Label5_5": 321,
    "Label5_6": 339,
    "Label5_7": 356,
    "Label6": 489,
    "Label6_3": 416,
    "Label6_4": 437,
    "Label6_5": 376,
    "Label6_6": 163,
    "Label6_7": 109,
    "Label6_8": 27,
    "Label7": 149,
    "Label7_1": 155,
    "Label7_2": 157,
    "Label8": 206,
    "Label8_1": 126,
    "Label8_5": 122,
    "Label8_7": 124,
    "Label9": 236,
    "Label9_1": 254,
    "Label9_2": 271,
    "Label9_3": 308,
    "Label9_4": 326,
    "Label9_5": 344,
    "Label9_6": 288,
    "Label9_7": 182,
    "Label9_8": 361,
    "LabelCapturaRGB_NO_BORRAR": 60,
    "labelCoColor": 64,
    "LabelCodigoSap": 68,
    "LabelDescripcion": 70,
    "LabelNombre": 72,
    "materiaPrima": 298,
    "materiaPrima_1": 371,
    "Materiaprimaprincipal_1": 139,
    "Materiaprimaprincipal_2": 138,
    "Materiaprimaprincipal1": 42,
    "Mssimilar1_7": 177,
    "Mssimilar1_8": 176,
    "Mssimilar4": 58,
    "Nombredecolor": 71,
    "Pantalla_GestionVanisados": 86,
    "Pantalla_Pantone": 194,
    "Pantalla_RGB_ENEAS": 273,
    "Pantalla_Vanisados": 314,
    "Pantonecdigo": 43,
    "Pantonecdigo_1": 40,
    "Rectangle1": 93,
    "Rectangle1_2": 413,
    "Rectangle1_3": 373,
    "Rectangle1_4": 160,
    "Rectangle1_5": 106,
    "Rectangle1_6": 24,
    "Rectangle10_1": 477,
    "Rectangle10_2": 478,
    "Rectangle10_3": 479,
    "Rectangle10_4": 476,
    "Rectangle11_2": 79,
    "Rectangle12": 449,
    "Rectangle15": 230,
    "Rectangle15_1": 148,
    "Rectangle15_2": 154,
    "Rectangle15_3": 302,
    "Rectangle15_5": 174,
    "Rectangle151": 56,
    "Rectangle16": 233,
    "Rectangle16_1": 305,
    "Rectangle16_3": 179,
    "Rectangle161": 59,
    "Rectangle18": 62,
    "Rectangle2": 178,
    "Rectangle211": 38,
    "Rectangle211_1": 466,
    "Rectangle3": 397,
    "Rectangle4": 153,
    "Rectangle40": 221,
    "Rectangle5": 216,
    "Rectangle5_1": 215,
    "Rectangle6": 405,
    "Rectangle6_2": 406,
    "Rectangle7": 469,
    "Rectangle73": 235,
    "Rectangle73_1": 307,
    "Rectangle73_3": 181,
    "Rectangle8": 88,
    "Rectangle86": 247,
    "Rectangle86_1": 319,
    "Rectangle86_2": 265,
    "Rectangle86_3": 337,
    "Rectangle86_4": 282,
    "Rectangle86_5": 355,
    "Rectangle87": 251,
    "Rectangle87_1": 323,
    "Rectangle87_2": 268,
    "Rectangle87_3": 341,
    "Rectangle87_4": 285,
    "Rectangle87_5": 358,
    "Rectangle89": 253,
    "Rectangle89_1": 325,
    "Rectangle89_2": 270,
    "Rectangle89_3": 343,
    "Rectangle89_4": 287,
    "Rectangle89_5": 360,
    "Rectangle9": 91,
    "ReporteRGBcolorCrystal": 129,
    "Separator2_1": 404,
    "Subtitle3_1": 514,
    "Subtitle3_2": 515,
    "Subtitle3_3": 516,
    "Subtitle3_4": 517,
    "TarjetaAlternativa": 173,
    "Test_7F478737223C4B69": 0,
    "TextInput1": 481,
    "TextInput1_1": 391,
    "TextInput1_10": 427,
    "TextInput1_2": 482,
    "TextInput1_3": 483,
    "TextInput1_4": 484,
    "TextInput1_6": 20,
    "TextInput1_7": 132,
    "TextInput1_8": 210,
    "TextInput1_9": 387,
    "TextInput2": 204,
    "TextInputB": 44,
    "TextInputG": 50,
    "TextInputR": 49,
    "TextInputReporteRGB1": 13,
    "TextoEtiquetaCodigocolor_1": 123,
    "TextoEtiquetaCodigoSAP": 11,
    "TextoEtiquetacolorCrystal": 9,
    "TextoEtiquetaNomColor": 7,
    "TextoEtiquetaPantone": 5,
    "TextoEtiquetaReporte": 12,
    "TextoEtiquetaReporte_1": 128,
    "Title2_2": 408,
    "Vector11": 250,
    "Vector11_1": 322
  },
  "ResourcesJsonIndices": {
    "Image-alert-circle": 1,
    "Image-charla": 3,
    "Image-charla (1)": 2,
    "Image-cuota": 4,
    "Image-image13189": 5,
    "Image-image13191": 6,
    "Image-image13193": 7,
    "Image-image13214": 8,
    "Image-image13215": 9,
    "Image-image13216": 10,
    "Image-intercambiar": 13,
    "Image-intercambiar (1)": 11,
    "Image-intercambiar (2)": 12,
    "Image-MicrosoftTeams-image (1)": 14,
    "Image-MicrosoftTeams-image (1)_1": 15,
    "Image-MicrosoftTeams-image (2)": 17,
    "Image-MicrosoftTeams-image (2) 1colorapp": 16,
    "Image-MicrosoftTeams-image (2)_1": 18,
    "Image-MicrosoftTeams-image (4)": 19,
    "Image-SampleImage": 0,
    "Image-VAyR": 20,
    "Image-Vector": 26,
    "Image-Vector (1)": 21,
    "Image-Vector (2)": 22,
    "Image-Vector (3)": 23,
    "Image-Vector (4)": 24,
    "Image-Vector (5)": 25
  },
  "RuleScreenIdWithoutScreen": {},
  "TemplateVersions": {},
  "VolatileProperties": {
    "AnalysisLoadTime": 1.8372385,
    "ControlCount": {
      "button": 65,
      "checkbox": 1,
      "circle": 3,
      "combobox": 7,
      "dropdown": 6,
      "gallery": 9,
      "galleryTemplate": 9,
      "groupContainer": 87,
      "icon": 42,
      "image": 38,
      "label": 176,
      "rectangle": 58,
      "screen": 6,
      "TestCase": 1,
      "TestSuite": 1,
      "text": 18
    },
    "DeserializationLoadTime": 3.1821467
  },
  "WasLocalDatabaseReferencesEmpty": true
}